material_ui-0.1.1.dist-info/DESCRIPTION.rst
material_ui-0.1.1.dist-info/WHEEL
material_ui-0.1.1.dist-info/top_level.txt
material_ui-0.1.1.dist-info/metadata.json
material_ui-0.1.1.dist-info/METADATA
material_ui-0.1.1.dist-info/RECORD
material_ui/demo.py
material_ui/__init__.py
material_ui/flatui/labels.py
material_ui/flatui/popups.kv
material_ui/flatui/scroll.kv
material_ui/flatui/scroll.py
material_ui/flatui/layouts.kv
material_ui/flatui/labels.kv
material_ui/flatui/popups.py
material_ui/flatui/flatui.py
material_ui/flatui/flatui.kv
material_ui/flatui/__init__.py
material_ui/flatui/layouts.py
material_ui/navigation/error.kv
material_ui/navigation/form.py
material_ui/navigation/error.py
material_ui/navigation/control.py
material_ui/navigation/form.kv
material_ui/navigation/control.kv
material_ui/navigation/nonetwork.py
material_ui/navigation/__init__.py
material_ui/navigation/images/nonetwork.png
material_ui/navigation/images/awsnap.png
material_ui/navigation/images/__transparent.png
