Metadata-Version: 2.0
Name: material-ui
Version: 0.1.1
Summary: Material UI for Kivy.
Home-page: https://github.com/Cuuuurzel/kivy-material-ui
Author: Federico Curzel
Author-email: cuuuurzel@gmail.com
License: UNKNOWN
Platform: UNKNOWN
